autosar_data-0.15.0.dist-info/METADATA
autosar_data-0.15.0.dist-info/WHEEL
autosar_data-0.15.0.dist-info/licenses/LICENSE-APACHE
autosar_data-0.15.0.dist-info/licenses/LICENSE-MIT
autosar_data/__init__.py
autosar_data/__init__.pyi
autosar_data/_autosar_data.cp312-win_amd64.pyd
autosar_data/abstraction/__init__.py
autosar_data/abstraction/__init__.pyi
autosar_data/abstraction/communication/__init__.py
autosar_data/abstraction/communication/__init__.pyi
autosar_data/abstraction/datatype/__init__.py
autosar_data/abstraction/datatype/__init__.pyi
autosar_data/abstraction/ecu_configuration/__init__.py
autosar_data/abstraction/ecu_configuration/__init__.pyi
autosar_data/abstraction/software_component/__init__.py
autosar_data/abstraction/software_component/__init__.pyi
autosar_data/py.typed
autosar_data-0.15.0.dist-info/RECORD
