Metadata-Version: 2.4
Name: autosar-data
Version: 0.15.0
Classifier: Intended Audience :: Developers
Classifier: Operating System :: MacOS :: MacOS X
Classifier: Operating System :: Microsoft :: Windows
Classifier: Operating System :: POSIX
Classifier: Programming Language :: Rust
Classifier: Programming Language :: Python :: Implementation :: CPython
Classifier: Programming Language :: Python :: Implementation :: PyPy
License-File: LICENSE-APACHE
License-File: LICENSE-MIT
Summary: read, write and modify Autosar arxml data using Python
Author-email: Daniel Thaler <daniel@dthaler.de>
Requires-Python: >=3.11
Project-URL: Source, https://github.com/DanielT/autosar-data-py
Project-URL: Tracker, https://github.com/DanielT/autosar-data-py/issues
Project-URL: Documentation, https://danielt.github.io/autosar-data-py/
